helperagent.py
shiftai.py
ShiftAI-1.0.0.dist-info/METADATA
ShiftAI-1.0.0.dist-info/WHEEL
ShiftAI-1.0.0.dist-info/top_level.txt
ShiftAI-1.0.0.dist-info/RECORD
