Metadata-Version: 2.1
Name: ShiftAI
Version: 1.0.0
Summary: ShiftAI - smart energy management for Home Assistant with load shifting recommendations.
Classifier: Programming Language :: Python :: 3
Classifier: License :: OSI Approved :: MIT License
Classifier: Operating System :: OS Independent
Requires-Dist: pandas
Requires-Dist: numpy
Requires-Dist: matplotlib
Requires-Dist: tqdm
Requires-Dist: datetime
Requires-Dist: xgboost
Requires-Dist: scikit-learn
Requires-Dist: statsmodels
Requires-Dist: interpret
Requires-Dist: shap
Requires-Dist: entsoe-py
Requires-Dist: beautifulsoup4 (==4.11.2)
Requires-Dist: IPython
Provides-Extra: dev
Requires-Dist: pytest ; extra == 'dev'
